npimage/__init__.py
npimage/align.py
npimage/graphics.py
npimage/imageio.py
npimage/nrrd_utils.py
npimage/operations.py
npimage/utils.py
npimage/vidio.py
numpyimage-3.5.1.dist-info/licenses/LICENSE
numpyimage-3.5.1.dist-info/METADATA
numpyimage-3.5.1.dist-info/WHEEL
numpyimage-3.5.1.dist-info/top_level.txt
numpyimage-3.5.1.dist-info/RECORD
