Metadata-Version: 2.4
Name: numpyimage
Version: 3.5.1
Summary: Load, save, & manipulate image files as numpy arrays
Author-email: Jasper Phelps <jasper.s.phelps@gmail.com>
License: MIT License
Project-URL: Repository, https://github.com/jasper-tms/npimage
Keywords: images,pixel arrays,image formats,convert,graphics,draw simple shapes
Classifier: Programming Language :: Python :: 3
Classifier: License :: OSI Approved :: MIT License
Classifier: Operating System :: OS Independent
Classifier: Development Status :: 5 - Production/Stable
Classifier: Topic :: Scientific/Engineering :: Image Processing
Requires-Python: >=3.6
License-File: LICENSE
Requires-Dist: numpy
Requires-Dist: tqdm
Requires-Dist: pillow
Requires-Dist: pillow-heif
Requires-Dist: tifffile
Requires-Dist: pynrrd
Requires-Dist: matplotlib
Requires-Dist: opencv-python-headless
Provides-Extra: all
Requires-Dist: av; extra == "all"
Dynamic: license-file
